customlogger/__init__.py
customlogger/custom_logger.py
customlogger/only_filter.py
customlogger/run_rotating_handler.py
customlogger/slack_handler.py
customlogger-0.3.1.dist-info/METADATA
customlogger-0.3.1.dist-info/RECORD
customlogger-0.3.1.dist-info/WHEEL
customlogger-0.3.1.dist-info/top_level.txt
tests/__init__.py
tests/test_custom_logger.py
