Metadata-Version: 2.1
Name: customlogger
Version: 0.3.1
Summary: custom logger class.
Home-page: UNKNOWN
Author: deresmos
Author-email: deresmos@gmail.com
License: MIT License
Keywords: logging,Logger,custom
Platform: UNKNOWN
Requires-Dist: requests
Requires-Dist: colorlog
